s1300017_learn/__init__.py
s1300017_learn/statistics/__init__.py
s1300017_learn/statistics/itemFrequencies.py
s1300017_learn/visualization/__init__.py
s1300017_learn/visualization/heatMap.py
studentID_learn-0.1.dist-info/METADATA
studentID_learn-0.1.dist-info/WHEEL
studentID_learn-0.1.dist-info/top_level.txt
studentID_learn-0.1.dist-info/RECORD
