Metadata-Version: 2.1
Name: studentID-learn
Version: 0.1
Summary: A package for learning purposes
Home-page: https://github.com/s1300017/s1300017_learn
Author: 仲野龍太朗
Author-email: s1300017@u-aizu.ac.jp
License: UNKNOWN
Platform: UNKNOWN
Requires-Dist: pami
